cover_cli/__init__.py
cover_cli/main.py
cover_cli-0.1.0.dist-info/LICENSE
cover_cli-0.1.0.dist-info/METADATA
cover_cli-0.1.0.dist-info/WHEEL
cover_cli-0.1.0.dist-info/entry_points.txt
cover_cli-0.1.0.dist-info/top_level.txt
cover_cli-0.1.0.dist-info/RECORD
